GoMartini/__init__.py
GoMartini/_version.py
GoMartini/create_goVirt.py
GoMartini-0.1.0.dist-info/LICENSE.txt
GoMartini-0.1.0.dist-info/METADATA
GoMartini-0.1.0.dist-info/WHEEL
GoMartini-0.1.0.dist-info/entry_points.txt
GoMartini-0.1.0.dist-info/top_level.txt
GoMartini-0.1.0.dist-info/RECORD
