Metadata-Version: 2.1
Name: GoMartini
Version: 0.1.0
Author: Sebastian Thallmair, Jonathan Barnoud, Paulo C. T. Souza
Author-email: Luís Borges-Araújo <lpborara@gmail.com>
Keywords: martini,MD,martinize,go model
Classifier: Development Status :: 4 - Beta
Classifier: Environment :: Console
Classifier: Intended Audience :: Developers
Classifier: Intended Audience :: Science/Research
Classifier: License :: OSI Approved :: Apache Software License
Classifier: Operating System :: OS Independent
Classifier: Programming Language :: Python :: 3
Classifier: Programming Language :: Python :: 3.6
Classifier: Programming Language :: Python :: 3.7
Classifier: Programming Language :: Python :: 3.8
Classifier: Programming Language :: Python :: 3.9
Classifier: Topic :: Scientific/Engineering :: Bio-Informatics
Classifier: Topic :: Scientific/Engineering :: Chemistry
License-File: LICENSE.txt
Requires-Dist: numpy ==1.*,>=1.22.1
Requires-Dist: importlib-metadata ; python_version < "3.8"
